awacs/__init__.py
awacs/a2c.py
awacs/a4b.py
awacs/access_analyzer.py
awacs/account.py
awacs/acm.py
awacs/acm_pca.py
awacs/activate.py
awacs/aiops.py
awacs/airflow.py
awacs/amplify.py
awacs/amplifybackend.py
awacs/amplifyuibuilder.py
awacs/aoss.py
awacs/apigateway.py
awacs/app_integrations.py
awacs/appconfig.py
awacs/appfabric.py
awacs/appflow.py
awacs/application_autoscaling.py
awacs/application_cost_profiler.py
awacs/application_signals.py
awacs/application_transformation.py
awacs/applicationinsights.py
awacs/appmesh.py
awacs/appmesh_preview.py
awacs/apprunner.py
awacs/appstream.py
awacs/appstudio.py
awacs/appsync.py
awacs/apptest.py
awacs/aps.py
awacs/arc_zonal_shift.py
awacs/arsenal.py
awacs/artifact.py
awacs/athena.py
awacs/auditmanager.py
awacs/autoscaling.py
awacs/autoscaling_plans.py
awacs/aws.py
awacs/aws_marketplace.py
awacs/aws_marketplace_management.py
awacs/aws_portal.py
awacs/awsconnector.py
awacs/awslambda.py
awacs/b2bi.py
awacs/backup.py
awacs/backup_gateway.py
awacs/backup_search.py
awacs/backup_storage.py
awacs/batch.py
awacs/bcm_data_exports.py
awacs/bcm_pricing_calculator.py
awacs/bedrock.py
awacs/billing.py
awacs/billingconductor.py
awacs/braket.py
awacs/budgets.py
awacs/bugbust.py
awacs/cases.py
awacs/cassandra.py
awacs/ce.py
awacs/chatbot.py
awacs/chime.py
awacs/cleanrooms.py
awacs/cleanrooms_ml.py
awacs/cloud9.py
awacs/clouddirectory.py
awacs/cloudformation.py
awacs/cloudfront.py
awacs/cloudfront_keyvaluestore.py
awacs/cloudhsm.py
awacs/cloudsearch.py
awacs/cloudshell.py
awacs/cloudtrail.py
awacs/cloudtrail_data.py
awacs/cloudwatch.py
awacs/codeartifact.py
awacs/codebuild.py
awacs/codecatalyst.py
awacs/codecommit.py
awacs/codeconnections.py
awacs/codedeploy.py
awacs/codedeploy_commands_secure.py
awacs/codeguru.py
awacs/codeguru_profiler.py
awacs/codeguru_reviewer.py
awacs/codeguru_security.py
awacs/codepipeline.py
awacs/codestar.py
awacs/codestar_connections.py
awacs/codestar_notifications.py
awacs/codewhisperer.py
awacs/cognito_identity.py
awacs-2.5.0.dist-info/LICENSE
awacs-2.5.0.dist-info/METADATA
awacs-2.5.0.dist-info/WHEEL
awacs-2.5.0.dist-info/top_level.txt
awacs-2.5.0.dist-info/RECORD
