Metadata-Version: 2.2
Name: awacs
Version: 2.5.0
Summary: AWS Access Policy Language creation library
Home-page: https://github.com/cloudtools/awacs
Author: Mark Peek
Author-email: mark@peek.org
License: New BSD license
Project-URL: Changelog, https://github.com/cloudtools/awacs/blob/master/CHANGELOG.md
Project-URL: Source, https://github.com/cloudtools/awacs
Project-URL: Tracker, https://github.com/cloudtools/awacs/issues
Classifier: Development Status :: 5 - Production/Stable
Classifier: Intended Audience :: Developers
Classifier: License :: OSI Approved :: BSD License
Classifier: Operating System :: OS Independent
Classifier: Programming Language :: Python
Classifier: Programming Language :: Python :: 3 :: Only
Classifier: Programming Language :: Python :: 3
Classifier: Programming Language :: Python :: 3.9
Classifier: Programming Language :: Python :: 3.10
Classifier: Programming Language :: Python :: 3.11
Classifier: Programming Language :: Python :: 3.12
Classifier: Programming Language :: Python :: 3.13
Requires-Python: >=3.9
License-File: LICENSE
